JsliteZhongwenWendang/README.md
JsliteZhongwenWendang/__init__.py
JsliteZhongwenWendang/__main__.py
JsliteZhongwenWendang/file.epub
JsliteZhongwenWendang/index.html
JsliteZhongwenWendang/css/__init__.py
JsliteZhongwenWendang/css/annotations.css
JsliteZhongwenWendang/css/main.css
JsliteZhongwenWendang/css/normalize.css
JsliteZhongwenWendang/css/popup.css
JsliteZhongwenWendang/font/__init__.py
JsliteZhongwenWendang/font/fontello.eot
JsliteZhongwenWendang/font/fontello.svg
JsliteZhongwenWendang/font/fontello.ttf
JsliteZhongwenWendang/font/fontello.woff
JsliteZhongwenWendang/img/__init__.py
JsliteZhongwenWendang/img/annotator-glyph-sprite.png
JsliteZhongwenWendang/img/annotator-icon-sprite.png
JsliteZhongwenWendang/img/apple-touch-icon.png
JsliteZhongwenWendang/img/cancelfullscreen.png
JsliteZhongwenWendang/img/close.png
JsliteZhongwenWendang/img/fullscreen.png
JsliteZhongwenWendang/img/loader.gif
JsliteZhongwenWendang/img/menu-icon.png
JsliteZhongwenWendang/img/save.png
JsliteZhongwenWendang/img/saved.png
JsliteZhongwenWendang/img/settings-s.png
JsliteZhongwenWendang/img/settings.png
JsliteZhongwenWendang/img/star.png
JsliteZhongwenWendang/js/__init__.py
JsliteZhongwenWendang/js/epub.js
JsliteZhongwenWendang/js/epub.min.js
JsliteZhongwenWendang/js/epub.min.map
JsliteZhongwenWendang/js/hooks.min.js
JsliteZhongwenWendang/js/hooks.min.map
JsliteZhongwenWendang/js/reader.js
JsliteZhongwenWendang/js/reader.js.map
JsliteZhongwenWendang/js/reader.min.js
JsliteZhongwenWendang/js/reader.min.map
JsliteZhongwenWendang/js/hooks/__init__.py
JsliteZhongwenWendang/js/hooks/extensions/__init__.py
JsliteZhongwenWendang/js/hooks/extensions/highlight.js
JsliteZhongwenWendang/js/libs/__init__.py
JsliteZhongwenWendang/js/libs/jquery.min.js
JsliteZhongwenWendang/js/libs/localforage.min.js
JsliteZhongwenWendang/js/libs/screenfull.js
JsliteZhongwenWendang/js/libs/screenfull.min.js
JsliteZhongwenWendang/js/libs/zip.min.js
JsliteZhongwenWendang/js/plugins/__init__.py
jslite_zhongwen_wendang-2024.3.1.0.dist-info/METADATA
jslite_zhongwen_wendang-2024.3.1.0.dist-info/WHEEL
jslite_zhongwen_wendang-2024.3.1.0.dist-info/entry_points.txt
jslite_zhongwen_wendang-2024.3.1.0.dist-info/top_level.txt
jslite_zhongwen_wendang-2024.3.1.0.dist-info/RECORD
